{
  "BurstVersion": "12fd8c57-ac57-41e8-88f3-e2a61ac3563b",
  "Assemblies": [
    {
      "FullName": "Unity.Burst, Version=0.0.0.0, Culture=neutral, PublicKeyToken=null",
      "LastWriteTime": "2021-02-23T19:28:21.2612452Z"
    },
    {
      "FullName": "mscorlib, Version=4.0.0.0, Culture=neutral, PublicKeyToken=b77a5c561934e089",
      "LastWriteTime": "2021-01-20T06:15:42Z"
    },
    {
      "FullName": "UnityEngine.CoreModule, Version=0.0.0.0, Culture=neutral, PublicKeyToken=null",
      "LastWriteTime": "2021-01-20T06:20:24Z"
    },
    {
      "FullName": "Unity.Barracuda, Version=1.2.1.0, Culture=neutral, PublicKeyToken=null",
      "LastWriteTime": "2021-02-23T19:28:22.1827965Z"
    },
    {
      "FullName": "mscorlib, Version=2.0.0.0, Culture=neutral, PublicKeyToken=b77a5c561934e089",
      "LastWriteTime": "2021-01-20T06:15:42Z"
    }
  ],
  "Functions": [
    {
      "FullName": "System.Int32 Unity.Burst.Intrinsics.X86::DoGetCSRTrampoline()",
      "ModuleOptionsHash": 8794384452606821980,
      "ModuleHash": "6dad7f382fb7af8baa51c9b46f050658",
      "LinkName": "CDCA4A5193BE5947",
      "AssemblyDependencyIndices": [
        0,
        1
      ]
    },
    {
      "FullName": "System.Void Unity.Burst.Intrinsics.X86::DoSetCSRTrampoline(System.Int32)",
      "ModuleOptionsHash": 8794384452606821980,
      "ModuleHash": "cf79ac3b9ce046d01f045d2740ab3c50",
      "LinkName": "801E9A000BB37B05",
      "AssemblyDependencyIndices": [
        0,
        1
      ]
    },
    {
      "FullName": "System.Void Unity.Jobs.IJobParallelForExtensions/ParallelForJobStruct`1<Unity.Barracuda.BurstCPUOps/ExpJob>::Execute(T&,System.IntPtr,System.IntPtr,Unity.Jobs.LowLevel.Unsafe.JobRanges&,System.Int32)",
      "ModuleOptionsHash": 8794384452606821980,
      "ModuleHash": "789976254a2dfb9070a78a9f501d8350",
      "LinkName": "53FE69074E5AFF26",
      "AssemblyDependencyIndices": [
        2,
        3,
        4,
        1
      ]
    }
  ]
}